apistar_sqlalchemy/__init__.py
apistar_sqlalchemy/components.py
apistar_sqlalchemy/database.py
apistar_sqlalchemy/event_hooks.py
apistar_sqlalchemy-0.3.2.dist-info/LICENSE.txt
apistar_sqlalchemy-0.3.2.dist-info/METADATA
apistar_sqlalchemy-0.3.2.dist-info/RECORD
apistar_sqlalchemy-0.3.2.dist-info/WHEEL
apistar_sqlalchemy-0.3.2.dist-info/top_level.txt
